lcu_driver/__init__.py
lcu_driver/connection.py
lcu_driver/connector.py
lcu_driver/exceptions.py
lcu_driver/utils.py
lcu_driver/events/__init__.py
lcu_driver/events/managers.py
lcu_driver/events/responses.py
lcu_driver-3.0.2.dist-info/LICENSE
lcu_driver-3.0.2.dist-info/METADATA
lcu_driver-3.0.2.dist-info/WHEEL
lcu_driver-3.0.2.dist-info/top_level.txt
lcu_driver-3.0.2.dist-info/RECORD
