Metadata-Version: 2.1
Name: lcu-driver
Version: 3.0.2
Home-page: https://github.com/sousa-andre/lcu-driver/
Author: André Matos de Sousa
Author-email: andrematosdesousa@gmail.com
License: MIT
Project-URL: Source, https://github.com/sousa-andre/lcu-driver/
License-File: LICENSE
Requires-Dist: aiohttp
Requires-Dist: psutil
